{"api_version":"1.0","results":[{"filing_form":"F3X","category_code_full":null,"committee_id":"C00639997","cand_office_district":"12","expenditure_amount":200.0,"memo_code_full":null,"candidate_prefix":null,"back_reference_schedule_name":null,"committee":{"party":null,"treasurer_name":"BALL, KRYSTAL","city":"WASHINGTON","committee_id":"C00639997","party_full":null,"state":"DC","state_full":"District Of Columbia","candidate_ids":[],"zip":"20005","street_2":null,"committee_type_full":"PAC - Qualified","name":"THE PEOPLE'S HOUSE PROJECT, INC.","cycle":2018,"organization_type":null,"committee_type":"Q","filing_frequency":"Q","organization_type_full":null,"street_1":"700 THIRTEENTH STREET","cycles":[2018],"designation_full":"Unauthorized","designation":"U"},"link_id":4071620181575982037,"filer_middle_name":null,"candidate_last_name":"NESMITH","dissemination_date":null,"conduit_committee_name":null,"memo_text":null,"original_sub_id":null,"report_year":2018,"independent_sign_name":"BALL, KRYSTAL","election_type_full":null,"payee_city":"LOUISVILLE","expenditure_date":"2018-05-11T00:00:00","category_code":null,"payee_state":"KY","schedule_type_full":"ITEMIZED INDEPENDENT EXPENDITURES","office_total_ytd":200.0,"notary_sign_name":null,"independent_sign_date":"2018-07-15T00:00:00","conduit_committee_city":null,"cand_office_state":"GA","filer_suffix":null,"filer_last_name":"BALL","file_number":1248393,"sub_id":"4071820181576228600","payee_first_name":"TOM","expenditure_description":"REIMBURSEMENT - SEE MEMO ENTRY","schedule_type":"SE","conduit_committee_street1":null,"back_reference_transaction_id":null,"payee_suffix":null,"is_notice":false,"payee_middle_name":null,"action_code":"A","conduit_committee_id":"C00651711","conduit_committee_state":null,"filer_first_name":"KRYSTAL","candidate":{"idx":63597,"candidate_id":"H8GA12052","two_year_period":2018.0},"memoed_subtotal":false,"payee_street_2":null,"filer_prefix":null,"payee_prefix":null,"notary_commission_expiration_date":null,"line_number":"24","payee_last_name":"JOHNSON","image_number":"201807159115641133","memo_code":null,"conduit_committee_zip":null,"candidate_office":"H","candidate_first_name":"MICHAEL","notary_sign_date":null,"payee_name":"JOHNSON, TOM","payee_street_1":"4024 SPRINGHILLD ROAD","candidate_id":"H8GA12052","candidate_middle_name":null,"pdf_url":"http:\/\/docquery.fec.gov\/cgi-bin\/fecimg\/?201807159115641133","payee_zip":"40207","candidate_name":"NESMITH, MICHAEL","support_oppose_indicator":"S","election_type":"P2018","action_code_full":"ADD","candidate_suffix":null,"report_type":"Q2","conduit_committee_street2":null},{"filing_form":"F3X","category_code_full":null,"committee_id":"C00639997","cand_office_district":"12","expenditure_amount":200.0,"memo_code_full":null,"candidate_prefix":null,"back_reference_schedule_name":"SE","committee":{"party":null,"treasurer_name":"BALL, KRYSTAL","city":"WASHINGTON","committee_id":"C00639997","party_full":null,"state":"DC","state_full":"District Of Columbia","candidate_ids":[],"zip":"20005","street_2":null,"committee_type_full":"PAC - Qualified","name":"THE PEOPLE'S HOUSE PROJECT, INC.","cycle":2018,"organization_type":null,"committee_type":"Q","filing_frequency":"Q","organization_type_full":null,"street_1":"700 THIRTEENTH STREET","cycles":[2018],"designation_full":"Unauthorized","designation":"U"},"link_id":4071620181575982037,"filer_middle_name":null,"candidate_last_name":"NESMITH","dissemination_date":null,"conduit_committee_name":null,"memo_text":null,"original_sub_id":null,"report_year":2018,"independent_sign_name":"BALL, KRYSTAL","election_type_full":null,"payee_city":"MENLO PARK","expenditure_date":"2018-05-11T00:00:00","category_code":null,"payee_state":"CA","schedule_type_full":"ITEMIZED INDEPENDENT EXPENDITURES","office_total_ytd":0.0,"notary_sign_name":null,"independent_sign_date":"2018-07-15T00:00:00","conduit_committee_city":null,"cand_office_state":"GA","filer_suffix":null,"filer_last_name":"BALL","file_number":1248393,"sub_id":"4071820181576228602","payee_first_name":null,"expenditure_description":"ADVERTISEMENTS","schedule_type":"SE","conduit_committee_street1":null,"back_reference_transaction_id":"24-01-00256-0006","payee_suffix":null,"is_notice":false,"payee_middle_name":null,"action_code":"A","conduit_committee_id":"C00651711","conduit_committee_state":null,"filer_first_name":"KRYSTAL","candidate":{"idx":63597,"candidate_id":"H8GA12052","two_year_period":2018.0},"memoed_subtotal":true,"payee_street_2":null,"filer_prefix":null,"payee_prefix":null,"notary_commission_expiration_date":null,"line_number":"24","payee_last_name":null,"image_number":"201807159115641133","memo_code":"X","conduit_committee_zip":null,"candidate_office":"H","candidate_first_name":"MICHAEL","notary_sign_date":null,"payee_name":"FACEBOOK - CORPORATE","payee_street_1":"1 HACKER WAY","candidate_id":"H8GA12052","candidate_middle_name":null,"pdf_url":"http:\/\/docquery.fec.gov\/cgi-bin\/fecimg\/?201807159115641133","payee_zip":"94025","candidate_name":"NESMITH, MICHAEL","support_oppose_indicator":"S","election_type":"P2018","action_code_full":"ADD","candidate_suffix":null,"report_type":"Q2","conduit_committee_street2":null}],"pagination":{"pages":1,"per_page":100,"count":2,"last_indexes":{"last_index":"4071820181576228602","last_expenditure_amount":200.0}}}
