{"api_version":"1.0","pagination":{"count":14,"per_page":100,"last_indexes":{"last_index":"4072620181576826661","last_expenditure_amount":20000.0},"pages":1},"results":[{"independent_sign_name":"ROZANSKY, ADAM","back_reference_schedule_name":null,"candidate_office_state":"SC","original_sub_id":null,"filer_middle_name":null,"action_code_full":"CHANGE","payee_street_1":"2001 L ST., NW","candidate_prefix":null,"candidate_last_name":"KIMBRELL","category_code":null,"candidate_party":"REP","candidate_first_name":"JOSHUA BRETT","back_reference_transaction_id":null,"image_number":"201809119121693637","memo_code":null,"candidate_middle_name":null,"dissemination_date":"2018-06-05T00:00:00","candidate_office_district":"04","pdf_url":"http:\/\/docquery.fec.gov\/cgi-bin\/fecimg\/?201809119121693637","conduit_committee_city":null,"committee_id":"C00432260","action_code":"C","payee_suffix":null,"memoed_subtotal":false,"notary_sign_date":null,"payee_first_name":null,"payee_middle_name":null,"sub_id":"4091320181591007647","expenditure_amount":6.46,"candidate":{"idx":71726,"candidate_id":"H8SC04318","two_year_period":2018.0},"link_id":4091120181590880581,"file_number":1260756,"filer_suffix":null,"payee_street_2":"STE. 600","expenditure_date":"2018-06-05T00:00:00","report_type":"M7","memo_code_full":null,"candidate_id":"H8SC04318","schedule_type_full":"ITEMIZED INDEPENDENT EXPENDITURES","candidate_office":"H","candidate_suffix":null,"memo_text":null,"payee_prefix":null,"conduit_committee_zip":null,"conduit_committee_id":"C00432260","payee_zip":"20036","notary_sign_name":null,"is_notice":false,"election_type_full":null,"payee_state":"DC","payee_name":"CLUB FOR GROWTH","conduit_committee_name":null,"schedule_type":"SE","committee":{"filing_frequency":"M","street_1":"2001 L ST NW SUITE 600","cycles":[2008,2010,2012,2014,2016,2018],"committee_id":"C00432260","committee_type":"Q","cycle":2018,"zip":"20036","organization_type_full":"Membership Organization","name":"CLUB FOR GROWTH PAC","party_full":null,"committee_type_full":"PAC - Qualified","treasurer_name":"ROZANSKY, ADAM","organization_type":"M","city":"WASHINGTON","street_2":null,"state":"DC","state_full":"District Of Columbia","party":null,"candidate_ids":[],"designation":"U","designation_full":"Unauthorized"},"category_code_full":null,"conduit_committee_street1":null,"filer_prefix":null,"support_oppose_indicator":"S","candidate_name":"KIMBRELL, JOSHUA BRETT","report_year":2018,"line_number":"24","filing_form":"F3X","conduit_committee_street2":null,"conduit_committee_state":null,"office_total_ytd":110.01,"expenditure_description":"INTERNET COMMUNICATIONS (FROM ADVANCE LINE 21)","election_type":"P2018","filer_last_name":"ROZANSKY","payee_last_name":null,"independent_sign_date":"2018-09-11T00:00:00","filer_first_name":"ADAM","notary_commission_expiration_date":null,"payee_city":"WASHINGTON"},{"independent_sign_name":"ROZANSKY, ADAM","back_reference_schedule_name":null,"candidate_office_state":"SC","original_sub_id":null,"filer_middle_name":null,"action_code_full":"CHANGE","payee_street_1":"2001 L ST., NW","candidate_prefix":null,"candidate_last_name":"KIMBRELL","category_code":null,"candidate_party":"REP","candidate_first_name":"JOSHUA BRETT","back_reference_transaction_id":null,"image_number":"201809119121693639","memo_code":null,"candidate_middle_name":null,"dissemination_date":"2018-06-06T00:00:00","candidate_office_district":"04","pdf_url":"http:\/\/docquery.fec.gov\/cgi-bin\/fecimg\/?201809119121693639","conduit_committee_city":null,"committee_id":"C00432260","action_code":"C","payee_suffix":null,"memoed_subtotal":false,"notary_sign_date":null,"payee_first_name":null,"payee_middle_name":null,"sub_id":"4091320181591007655","expenditure_amount":6.46,"candidate":{"idx":71726,"candidate_id":"H8SC04318","two_year_period":2018.0},"link_id":4091120181590880581,"file_number":1260756,"filer_suffix":null,"payee_street_2":"STE. 600","expenditure_date":"2018-06-06T00:00:00","report_type":"M7","memo_code_full":null,"candidate_id":"H8SC04318","schedule_type_full":"ITEMIZED INDEPENDENT EXPENDITURES","candidate_office":"H","candidate_suffix":null,"memo_text":null,"payee_prefix":null,"conduit_committee_zip":null,"conduit_committee_id":"C00432260","payee_zip":"20036","notary_sign_name":null,"is_notice":false,"election_type_full":null,"payee_state":"DC","payee_name":"CLUB FOR GROWTH","conduit_committee_name":null,"schedule_type":"SE","committee":{"filing_frequency":"M","street_1":"2001 L ST NW SUITE 600","cycles":[2008,2010,2012,2014,2016,2018],"committee_id":"C00432260","committee_type":"Q","cycle":2018,"zip":"20036","organization_type_full":"Membership Organization","name":"CLUB FOR GROWTH PAC","party_full":null,"committee_type_full":"PAC - Qualified","treasurer_name":"ROZANSKY, ADAM","organization_type":"M","city":"WASHINGTON","street_2":null,"state":"DC","state_full":"District Of Columbia","party":null,"candidate_ids":[],"designation":"U","designation_full":"Unauthorized"},"category_code_full":null,"conduit_committee_street1":null,"filer_prefix":null,"support_oppose_indicator":"S","candidate_name":"KIMBRELL, JOSHUA BRETT","report_year":2018,"line_number":"24","filing_form":"F3X","conduit_committee_street2":null,"conduit_committee_state":null,"office_total_ytd":456.87,"expenditure_description":"INTERNET COMMUNICATIONS (FROM ADVANCE LINE 21)","election_type":"P2018","filer_last_name":"ROZANSKY","payee_last_name":null,"independent_sign_date":"2018-09-11T00:00:00","filer_first_name":"ADAM","notary_commission_expiration_date":null,"payee_city":"WASHINGTON"},{"independent_sign_name":"ROZANSKY, ADAM","back_reference_schedule_name":null,"candidate_office_state":"SC","original_sub_id":null,"filer_middle_name":null,"action_code_full":"CHANGE","payee_street_1":"2001 L ST., NW","candidate_prefix":null,"candidate_last_name":"KIMBRELL","category_code":null,"candidate_party":"REP","candidate_first_name":"JOSHUA BRETT","back_reference_transaction_id":null,"image_number":"201809119121693645","memo_code":null,"candidate_middle_name":null,"dissemination_date":"2018-06-11T00:00:00","candidate_office_district":"04","pdf_url":"http:\/\/docquery.fec.gov\/cgi-bin\/fecimg\/?201809119121693645","conduit_committee_city":null,"committee_id":"C00432260","action_code":"C","payee_suffix":null,"memoed_subtotal":false,"notary_sign_date":null,"payee_first_name":null,"payee_middle_name":null,"sub_id":"4091320181591007679","expenditure_amount":12.92,"candidate":{"idx":71726,"candidate_id":"H8SC04318","two_year_period":2018.0},"link_id":4091120181590880581,"file_number":1260756,"filer_suffix":null,"payee_street_2":"STE. 600","expenditure_date":"2018-06-11T00:00:00","report_type":"M7","memo_code_full":null,"candidate_id":"H8SC04318","schedule_type_full":"ITEMIZED INDEPENDENT EXPENDITURES","candidate_office":"H","candidate_suffix":null,"memo_text":null,"payee_prefix":null,"conduit_committee_zip":null,"conduit_committee_id":"C00432260","payee_zip":"20036","notary_sign_name":null,"is_notice":false,"election_type_full":null,"payee_state":"DC","payee_name":"CLUB FOR GROWTH","conduit_committee_name":null,"schedule_type":"SE","committee":{"filing_frequency":"M","street_1":"2001 L ST NW SUITE 600","cycles":[2008,2010,2012,2014,2016,2018],"committee_id":"C00432260","committee_type":"Q","cycle":2018,"zip":"20036","organization_type_full":"Membership Organization","name":"CLUB FOR GROWTH PAC","party_full":null,"committee_type_full":"PAC - Qualified","treasurer_name":"ROZANSKY, ADAM","organization_type":"M","city":"WASHINGTON","street_2":null,"state":"DC","state_full":"District Of Columbia","party":null,"candidate_ids":[],"designation":"U","designation_full":"Unauthorized"},"category_code_full":null,"conduit_committee_street1":null,"filer_prefix":null,"support_oppose_indicator":"S","candidate_name":"KIMBRELL, JOSHUA BRETT","report_year":2018,"line_number":"24","filing_form":"F3X","conduit_committee_street2":null,"conduit_committee_state":null,"office_total_ytd":469.79,"expenditure_description":"INTERNET COMMUNICATIONS (FROM ADVANCE LINE 21)","election_type":"P2018","filer_last_name":"ROZANSKY","payee_last_name":null,"independent_sign_date":"2018-09-11T00:00:00","filer_first_name":"ADAM","notary_commission_expiration_date":null,"payee_city":"WASHINGTON"},{"independent_sign_name":"ROZANSKY, ADAM","back_reference_schedule_name":null,"candidate_office_state":"SC","original_sub_id":null,"filer_middle_name":null,"action_code_full":"CHANGE","payee_street_1":"2001 L ST., NW","candidate_prefix":null,"candidate_last_name":"KIMBRELL","category_code":null,"candidate_party":"REP","candidate_first_name":"JOSHUA BRETT","back_reference_transaction_id":null,"image_number":"201809119121693637","memo_code":null,"candidate_middle_name":null,"dissemination_date":"2018-06-05T00:00:00","candidate_office_district":"04","pdf_url":"http:\/\/docquery.fec.gov\/cgi-bin\/fecimg\/?201809119121693637","conduit_committee_city":null,"committee_id":"C00432260","action_code":"C","payee_suffix":null,"memoed_subtotal":false,"notary_sign_date":null,"payee_first_name":null,"payee_middle_name":null,"sub_id":"4091320181591007645","expenditure_amount":103.55,"candidate":{"idx":71726,"candidate_id":"H8SC04318","two_year_period":2018.0},"link_id":4091120181590880581,"file_number":1260756,"filer_suffix":null,"payee_street_2":"STE. 600","expenditure_date":"2018-06-05T00:00:00","report_type":"M7","memo_code_full":null,"candidate_id":"H8SC04318","schedule_type_full":"ITEMIZED INDEPENDENT EXPENDITURES","candidate_office":"H","candidate_suffix":null,"memo_text":null,"payee_prefix":null,"conduit_committee_zip":null,"conduit_committee_id":"C00432260","payee_zip":"20036","notary_sign_name":null,"is_notice":false,"election_type_full":null,"payee_state":"DC","payee_name":"CLUB FOR GROWTH","conduit_committee_name":null,"schedule_type":"SE","committee":{"filing_frequency":"M","street_1":"2001 L ST NW SUITE 600","cycles":[2008,2010,2012,2014,2016,2018],"committee_id":"C00432260","committee_type":"Q","cycle":2018,"zip":"20036","organization_type_full":"Membership Organization","name":"CLUB FOR GROWTH PAC","party_full":null,"committee_type_full":"PAC - Qualified","treasurer_name":"ROZANSKY, ADAM","organization_type":"M","city":"WASHINGTON","street_2":null,"state":"DC","state_full":"District Of Columbia","party":null,"candidate_ids":[],"designation":"U","designation_full":"Unauthorized"},"category_code_full":null,"conduit_committee_street1":null,"filer_prefix":null,"support_oppose_indicator":"S","candidate_name":"KIMBRELL, JOSHUA BRETT","report_year":2018,"line_number":"24","filing_form":"F3X","conduit_committee_street2":null,"conduit_committee_state":null,"office_total_ytd":103.55,"expenditure_description":"PRESS RELEASE (FROM ADVANCE LINE 21)","election_type":"P2018","filer_last_name":"ROZANSKY","payee_last_name":null,"independent_sign_date":"2018-09-11T00:00:00","filer_first_name":"ADAM","notary_commission_expiration_date":null,"payee_city":"WASHINGTON"},{"independent_sign_name":"ROZANSKY, ADAM","back_reference_schedule_name":null,"candidate_office_state":"SC","original_sub_id":null,"filer_middle_name":null,"action_code_full":"ADD","payee_street_1":"2001 L ST., NW","candidate_prefix":null,"candidate_last_name":"KIMBRELL","category_code":null,"candidate_party":"REP","candidate_first_name":"JOSHUA BRETT","back_reference_transaction_id":null,"image_number":"201807209117756106","memo_code":null,"candidate_middle_name":null,"dissemination_date":"2018-06-09T00:00:00","candidate_office_district":"04","pdf_url":"http:\/\/docquery.fec.gov\/cgi-bin\/fecimg\/?201807209117756106","conduit_committee_city":null,"committee_id":"C00487470","action_code":"A","payee_suffix":null,"memoed_subtotal":false,"notary_sign_date":null,"payee_first_name":null,"payee_middle_name":null,"sub_id":"4072620181576826601","expenditure_amount":141.4,"candidate":{"idx":71726,"candidate_id":"H8SC04318","two_year_period":2018.0},"link_id":4072020181576445397,"file_number":1251346,"filer_suffix":null,"payee_street_2":"STE. 600","expenditure_date":"2018-06-09T00:00:00","report_type":"M7","memo_code_full":null,"candidate_id":"H8SC04318","schedule_type_full":"ITEMIZED INDEPENDENT EXPENDITURES","candidate_office":"H","candidate_suffix":null,"memo_text":null,"payee_prefix":null,"conduit_committee_zip":null,"conduit_committee_id":"C00487470","payee_zip":"20036","notary_sign_name":null,"is_notice":false,"election_type_full":null,"payee_state":"DC","payee_name":"CLUB FOR GROWTH","conduit_committee_name":null,"schedule_type":"SE","committee":{"filing_frequency":"M","street_1":"2001 L ST NW STE 600","cycles":[2010,2012,2014,2016,2018],"committee_id":"C00487470","committee_type":"O","cycle":2018,"zip":"20036","organization_type_full":null,"name":"CLUB FOR GROWTH ACTION","party_full":null,"committee_type_full":"Super PAC (Independent Expenditure-Only)","treasurer_name":"ADAM ROZANSKY","organization_type":null,"city":"WASHINGTON","street_2":null,"state":"DC","state_full":"District Of Columbia","party":null,"candidate_ids":[],"designation":"U","designation_full":"Unauthorized"},"category_code_full":null,"conduit_committee_street1":null,"filer_prefix":null,"support_oppose_indicator":"S","candidate_name":"KIMBRELL, JOSHUA BRETT","report_year":2018,"line_number":"24","filing_form":"F3X","conduit_committee_street2":null,"conduit_committee_state":null,"office_total_ytd":408704.28,"expenditure_description":"PHONE BANK COSTS (FROM ADVANCE LINE 21)","election_type":"P2018","filer_last_name":"ROZANSKY","payee_last_name":null,"independent_sign_date":"2018-07-20T00:00:00","filer_first_name":"ADAM","notary_commission_expiration_date":null,"payee_city":"WASHINGTON"},{"independent_sign_name":"ROZANSKY, ADAM","back_reference_schedule_name":null,"candidate_office_state":"SC","original_sub_id":null,"filer_middle_name":null,"action_code_full":"ADD","payee_street_1":"2001 L ST., NW","candidate_prefix":null,"candidate_last_name":"KIMBRELL","category_code":null,"candidate_party":"REP","candidate_first_name":"JOSHUA BRETT","back_reference_transaction_id":null,"image_number":"201807209117756106","memo_code":null,"candidate_middle_name":null,"dissemination_date":"2018-06-08T00:00:00","candidate_office_district":"04","pdf_url":"http:\/\/docquery.fec.gov\/cgi-bin\/fecimg\/?201807209117756106","conduit_committee_city":null,"committee_id":"C00487470","action_code":"A","payee_suffix":null,"memoed_subtotal":false,"notary_sign_date":null,"payee_first_name":null,"payee_middle_name":null,"sub_id":"4072620181576826599","expenditure_amount":195.65,"candidate":{"idx":71726,"candidate_id":"H8SC04318","two_year_period":2018.0},"link_id":4072020181576445397,"file_number":1251346,"filer_suffix":null,"payee_street_2":"STE. 600","expenditure_date":"2018-06-08T00:00:00","report_type":"M7","memo_code_full":null,"candidate_id":"H8SC04318","schedule_type_full":"ITEMIZED INDEPENDENT EXPENDITURES","candidate_office":"H","candidate_suffix":null,"memo_text":null,"payee_prefix":null,"conduit_committee_zip":null,"conduit_committee_id":"C00487470","payee_zip":"20036","notary_sign_name":null,"is_notice":false,"election_type_full":null,"payee_state":"DC","payee_name":"CLUB FOR GROWTH","conduit_committee_name":null,"schedule_type":"SE","committee":{"filing_frequency":"M","street_1":"2001 L ST NW STE 600","cycles":[2010,2012,2014,2016,2018],"committee_id":"C00487470","committee_type":"O","cycle":2018,"zip":"20036","organization_type_full":null,"name":"CLUB FOR GROWTH ACTION","party_full":null,"committee_type_full":"Super PAC (Independent Expenditure-Only)","treasurer_name":"ADAM ROZANSKY","organization_type":null,"city":"WASHINGTON","street_2":null,"state":"DC","state_full":"District Of Columbia","party":null,"candidate_ids":[],"designation":"U","designation_full":"Unauthorized"},"category_code_full":null,"conduit_committee_street1":null,"filer_prefix":null,"support_oppose_indicator":"S","candidate_name":"KIMBRELL, JOSHUA BRETT","report_year":2018,"line_number":"24","filing_form":"F3X","conduit_committee_street2":null,"conduit_committee_state":null,"office_total_ytd":365562.88,"expenditure_description":"DIGITAL AD PRODUCTION COSTS (FROM ADVANCE LINE 21)","election_type":"P2018","filer_last_name":"ROZANSKY","payee_last_name":null,"independent_sign_date":"2018-07-20T00:00:00","filer_first_name":"ADAM","notary_commission_expiration_date":null,"payee_city":"WASHINGTON"},{"independent_sign_name":"ROZANSKY, ADAM","back_reference_schedule_name":null,"candidate_office_state":"SC","original_sub_id":null,"filer_middle_name":null,"action_code_full":"CHANGE","payee_street_1":"2001 L ST., NW","candidate_prefix":null,"candidate_last_name":"KIMBRELL","category_code":null,"candidate_party":"REP","candidate_first_name":"JOSHUA BRETT","back_reference_transaction_id":null,"image_number":"201809119121693638","memo_code":null,"candidate_middle_name":null,"dissemination_date":"2018-06-06T00:00:00","candidate_office_district":"04","pdf_url":"http:\/\/docquery.fec.gov\/cgi-bin\/fecimg\/?201809119121693638","conduit_committee_city":null,"committee_id":"C00432260","action_code":"C","payee_suffix":null,"memoed_subtotal":false,"notary_sign_date":null,"payee_first_name":null,"payee_middle_name":null,"sub_id":"4091320181591007649","expenditure_amount":340.4,"candidate":{"idx":71726,"candidate_id":"H8SC04318","two_year_period":2018.0},"link_id":4091120181590880581,"file_number":1260756,"filer_suffix":null,"payee_street_2":"STE. 600","expenditure_date":"2018-06-06T00:00:00","report_type":"M7","memo_code_full":null,"candidate_id":"H8SC04318","schedule_type_full":"ITEMIZED INDEPENDENT EXPENDITURES","candidate_office":"H","candidate_suffix":null,"memo_text":null,"payee_prefix":null,"conduit_committee_zip":null,"conduit_committee_id":"C00432260","payee_zip":"20036","notary_sign_name":null,"is_notice":false,"election_type_full":null,"payee_state":"DC","payee_name":"CLUB FOR GROWTH","conduit_committee_name":null,"schedule_type":"SE","committee":{"filing_frequency":"M","street_1":"2001 L ST NW SUITE 600","cycles":[2008,2010,2012,2014,2016,2018],"committee_id":"C00432260","committee_type":"Q","cycle":2018,"zip":"20036","organization_type_full":"Membership Organization","name":"CLUB FOR GROWTH PAC","party_full":null,"committee_type_full":"PAC - Qualified","treasurer_name":"ROZANSKY, ADAM","organization_type":"M","city":"WASHINGTON","street_2":null,"state":"DC","state_full":"District Of Columbia","party":null,"candidate_ids":[],"designation":"U","designation_full":"Unauthorized"},"category_code_full":null,"conduit_committee_street1":null,"filer_prefix":null,"support_oppose_indicator":"S","candidate_name":"KIMBRELL, JOSHUA BRETT","report_year":2018,"line_number":"24","filing_form":"F3X","conduit_committee_street2":null,"conduit_committee_state":null,"office_total_ytd":450.41,"expenditure_description":"EMAIL COSTS (FROM ADVANCE LINE 21)","election_type":"P2018","filer_last_name":"ROZANSKY","payee_last_name":null,"independent_sign_date":"2018-09-11T00:00:00","filer_first_name":"ADAM","notary_commission_expiration_date":null,"payee_city":"WASHINGTON"},{"independent_sign_name":"MAXWELL, THOMAS F. III","back_reference_schedule_name":null,"candidate_office_state":"SC","original_sub_id":null,"filer_middle_name":"F.","action_code_full":"ADD","payee_street_1":"301 N MAIN STREET","candidate_prefix":null,"candidate_last_name":"KIMBRELL","category_code":null,"candidate_party":"REP","candidate_first_name":"JOSHUA","back_reference_transaction_id":null,"image_number":"201807119115305013","memo_code":null,"candidate_middle_name":"BRETT","dissemination_date":"2018-06-08T00:00:00","candidate_office_district":"04","pdf_url":"http:\/\/docquery.fec.gov\/cgi-bin\/fecimg\/?201807119115305013","conduit_committee_city":null,"committee_id":"C00532630","action_code":"A","payee_suffix":null,"memoed_subtotal":false,"notary_sign_date":null,"payee_first_name":null,"payee_middle_name":null,"sub_id":"4071120181575571981","expenditure_amount":884.29,"candidate":{"idx":71726,"candidate_id":"H8SC04318","two_year_period":2018.0},"link_id":4071120181575552597,"file_number":1243760,"filer_suffix":"III","payee_street_2":"STE. 2200","expenditure_date":"2018-06-21T00:00:00","report_type":"Q2","memo_code_full":null,"candidate_id":"H8SC04318","schedule_type_full":"ITEMIZED INDEPENDENT EXPENDITURES","candidate_office":"H","candidate_suffix":null,"memo_text":null,"payee_prefix":null,"conduit_committee_zip":null,"conduit_committee_id":"C00532630","payee_zip":"70825","notary_sign_name":null,"is_notice":false,"election_type_full":null,"payee_state":"LA","payee_name":"LAGNIAPPE COMMUNICATIONS GROUP","conduit_committee_name":null,"schedule_type":"SE","committee":{"filing_frequency":"M","street_1":"4703 WOODWAY LANE, NW","cycles":[2012,2014,2016,2018],"committee_id":"C00532630","committee_type":"O","cycle":2018,"zip":"20016","organization_type_full":null,"name":"OUR AMERICAN CENTURY","party_full":null,"committee_type_full":"Super PAC (Independent Expenditure-Only)","treasurer_name":"MAXWELL, THOMAS F. III","organization_type":null,"city":"WASHINGTON","street_2":null,"state":"DC","state_full":"District Of Columbia","party":null,"candidate_ids":[],"designation":"U","designation_full":"Unauthorized"},"category_code_full":null,"conduit_committee_street1":null,"filer_prefix":null,"support_oppose_indicator":"O","candidate_name":"KIMBRELL, JOSHUA BRETT","report_year":2018,"line_number":"24","filing_form":"F3X","conduit_committee_street2":null,"conduit_committee_state":null,"office_total_ytd":884.29,"expenditure_description":"DIGITAL MEDIA - PLACEMENT & PRODUCTION","election_type":"P2018","filer_last_name":"MAXWELL","payee_last_name":null,"independent_sign_date":"2018-07-11T00:00:00","filer_first_name":"THOMAS","notary_commission_expiration_date":null,"payee_city":"BATON ROUGE"},{"independent_sign_name":"ROZANSKY, ADAM","back_reference_schedule_name":null,"candidate_office_state":"SC","original_sub_id":null,"filer_middle_name":null,"action_code_full":"ADD","payee_street_1":"2001 L ST., NW","candidate_prefix":null,"candidate_last_name":"KIMBRELL","category_code":null,"candidate_party":"REP","candidate_first_name":"JOSHUA BRETT","back_reference_transaction_id":null,"image_number":"201807209117756101","memo_code":null,"candidate_middle_name":null,"dissemination_date":"2018-06-09T00:00:00","candidate_office_district":"04","pdf_url":"http:\/\/docquery.fec.gov\/cgi-bin\/fecimg\/?201807209117756101","conduit_committee_city":null,"committee_id":"C00487470","action_code":"A","payee_suffix":null,"memoed_subtotal":false,"notary_sign_date":null,"payee_first_name":null,"payee_middle_name":null,"sub_id":"4072620181576826579","expenditure_amount":934.0,"candidate":{"idx":71726,"candidate_id":"H8SC04318","two_year_period":2018.0},"link_id":4072020181576445397,"file_number":1251346,"filer_suffix":null,"payee_street_2":"STE. 600-A","expenditure_date":"2018-06-08T00:00:00","report_type":"M7","memo_code_full":null,"candidate_id":"H8SC04318","schedule_type_full":"ITEMIZED INDEPENDENT EXPENDITURES","candidate_office":"H","candidate_suffix":null,"memo_text":null,"payee_prefix":null,"conduit_committee_zip":null,"conduit_committee_id":"C00487470","payee_zip":"20036","notary_sign_name":null,"is_notice":false,"election_type_full":null,"payee_state":"DC","payee_name":"CFG LABS, INC.","conduit_committee_name":null,"schedule_type":"SE","committee":{"filing_frequency":"M","street_1":"2001 L ST NW STE 600","cycles":[2010,2012,2014,2016,2018],"committee_id":"C00487470","committee_type":"O","cycle":2018,"zip":"20036","organization_type_full":null,"name":"CLUB FOR GROWTH ACTION","party_full":null,"committee_type_full":"Super PAC (Independent Expenditure-Only)","treasurer_name":"ADAM ROZANSKY","organization_type":null,"city":"WASHINGTON","street_2":null,"state":"DC","state_full":"District Of Columbia","party":null,"candidate_ids":[],"designation":"U","designation_full":"Unauthorized"},"category_code_full":null,"conduit_committee_street1":null,"filer_prefix":null,"support_oppose_indicator":"S","candidate_name":"KIMBRELL, JOSHUA BRETT","report_year":2018,"line_number":"24","filing_form":"F3X","conduit_committee_street2":null,"conduit_committee_state":null,"office_total_ytd":365367.23,"expenditure_description":"DATA ANALYTICS","election_type":"P2018","filer_last_name":"ROZANSKY","payee_last_name":null,"independent_sign_date":"2018-07-20T00:00:00","filer_first_name":"ADAM","notary_commission_expiration_date":null,"payee_city":"WASHINGTON"},{"independent_sign_name":"ROZANSKY, ADAM","back_reference_schedule_name":null,"candidate_office_state":"SC","original_sub_id":null,"filer_middle_name":null,"action_code_full":"ADD","payee_street_1":"3112 ROKEBY ROAD","candidate_prefix":null,"candidate_last_name":"KIMBRELL","category_code":null,"candidate_party":"REP","candidate_first_name":"JOSHUA BRETT","back_reference_transaction_id":null,"image_number":"201807209117756125","memo_code":null,"candidate_middle_name":null,"dissemination_date":"2018-06-08T00:00:00","candidate_office_district":"04","pdf_url":"http:\/\/docquery.fec.gov\/cgi-bin\/fecimg\/?201807209117756125","conduit_committee_city":null,"committee_id":"C00487470","action_code":"A","payee_suffix":null,"memoed_subtotal":false,"notary_sign_date":null,"payee_first_name":null,"payee_middle_name":null,"sub_id":"4072620181576826675","expenditure_amount":3000.0,"candidate":{"idx":71726,"candidate_id":"H8SC04318","two_year_period":2018.0},"link_id":4072020181576445397,"file_number":1251346,"filer_suffix":null,"payee_street_2":null,"expenditure_date":"2018-06-08T00:00:00","report_type":"M7","memo_code_full":null,"candidate_id":"H8SC04318","schedule_type_full":"ITEMIZED INDEPENDENT EXPENDITURES","candidate_office":"H","candidate_suffix":null,"memo_text":null,"payee_prefix":null,"conduit_committee_zip":null,"conduit_committee_id":"C00487470","payee_zip":"20144","notary_sign_name":null,"is_notice":false,"election_type_full":null,"payee_state":"VA","payee_name":"WARFIELD AND COMPANY","conduit_committee_name":null,"schedule_type":"SE","committee":{"filing_frequency":"M","street_1":"2001 L ST NW STE 600","cycles":[2010,2012,2014,2016,2018],"committee_id":"C00487470","committee_type":"O","cycle":2018,"zip":"20036","organization_type_full":null,"name":"CLUB FOR GROWTH ACTION","party_full":null,"committee_type_full":"Super PAC (Independent Expenditure-Only)","treasurer_name":"ADAM ROZANSKY","organization_type":null,"city":"WASHINGTON","street_2":null,"state":"DC","state_full":"District Of Columbia","party":null,"candidate_ids":[],"designation":"U","designation_full":"Unauthorized"},"category_code_full":null,"conduit_committee_street1":null,"filer_prefix":null,"support_oppose_indicator":"S","candidate_name":"KIMBRELL, JOSHUA BRETT","report_year":2018,"line_number":"24","filing_form":"F3X","conduit_committee_street2":null,"conduit_committee_state":null,"office_total_ytd":408562.88,"expenditure_description":"DIGITAL AD PRODUCTION COSTS","election_type":"P2018","filer_last_name":"ROZANSKY","payee_last_name":null,"independent_sign_date":"2018-07-20T00:00:00","filer_first_name":"ADAM","notary_commission_expiration_date":null,"payee_city":"DELAPLANE"},{"independent_sign_name":null,"back_reference_schedule_name":null,"candidate_office_state":"SC","original_sub_id":null,"filer_middle_name":null,"action_code_full":"ADD","payee_street_1":"2300 CLARENDON BOULEVARD","candidate_prefix":null,"candidate_last_name":"KIMBRELL","category_code":null,"candidate_party":"REP","candidate_first_name":"JOSHUA BRETT","back_reference_transaction_id":null,"image_number":"201807159115526695","memo_code":null,"candidate_middle_name":null,"dissemination_date":null,"candidate_office_district":"04","pdf_url":"http:\/\/docquery.fec.gov\/cgi-bin\/fecimg\/?201807159115526695","conduit_committee_city":null,"committee_id":"C90017294","action_code":"A","payee_suffix":null,"memoed_subtotal":false,"notary_sign_date":null,"payee_first_name":null,"payee_middle_name":null,"sub_id":"4072620181576818523","expenditure_amount":12500.0,"candidate":{"idx":71726,"candidate_id":"H8SC04318","two_year_period":2018.0},"link_id":4071520181575953663,"file_number":1247725,"filer_suffix":null,"payee_street_2":"SUITE 303","expenditure_date":"2018-06-07T00:00:00","report_type":"Q2","memo_code_full":null,"candidate_id":"H8SC04318","schedule_type_full":"FOR EACH INDEPENDENT EXPENDITURE MADE","candidate_office":"H","candidate_suffix":null,"memo_text":null,"payee_prefix":null,"conduit_committee_zip":null,"conduit_committee_id":null,"payee_zip":"22201","notary_sign_name":null,"is_notice":false,"election_type_full":"PRIMARY","payee_state":"VA","payee_name":"ADVANTAGE DIRECT","conduit_committee_name":null,"schedule_type":"SE-F57","committee":{"filing_frequency":"Q","street_1":"2600 VIRGINIA AVE NW","cycles":[2018],"committee_id":"C90017294","committee_type":"I","cycle":2018,"zip":"20037","organization_type_full":null,"name":"CLA, INC.","party_full":null,"committee_type_full":"Independent Expenditor (Person or Group)","treasurer_name":null,"organization_type":null,"city":"WASHINGTON","street_2":"SUITE 505","state":"DC","state_full":"District Of Columbia","party":null,"candidate_ids":[],"designation":"U","designation_full":"Unauthorized"},"category_code_full":null,"conduit_committee_street1":null,"filer_prefix":null,"support_oppose_indicator":"S","candidate_name":"KIMBRELL, JOSHUA BRETT","report_year":2018,"line_number":null,"filing_form":"F5","conduit_committee_street2":null,"conduit_committee_state":null,"office_total_ytd":12500.0,"expenditure_description":"INDEPENDENT EXPENDITURE FOR","election_type":"P2018","filer_last_name":null,"payee_last_name":null,"independent_sign_date":null,"filer_first_name":null,"notary_commission_expiration_date":null,"payee_city":"ARLINGTON"},{"independent_sign_name":null,"back_reference_schedule_name":null,"candidate_office_state":"SC","original_sub_id":null,"filer_middle_name":null,"action_code_full":"ADD","payee_street_1":"P.O. BOX 25093","candidate_prefix":null,"candidate_last_name":"KIMBRELL","category_code":null,"candidate_party":"REP","candidate_first_name":"JOSHUA BRETT","back_reference_transaction_id":null,"image_number":"201807159115526697","memo_code":null,"candidate_middle_name":null,"dissemination_date":null,"candidate_office_district":"04","pdf_url":"http:\/\/docquery.fec.gov\/cgi-bin\/fecimg\/?201807159115526697","conduit_committee_city":null,"committee_id":"C90017294","action_code":"A","payee_suffix":null,"memoed_subtotal":false,"notary_sign_date":null,"payee_first_name":null,"payee_middle_name":null,"sub_id":"4072620181576818529","expenditure_amount":12824.0,"candidate":{"idx":71726,"candidate_id":"H8SC04318","two_year_period":2018.0},"link_id":4071520181575953663,"file_number":1247725,"filer_suffix":null,"payee_street_2":null,"expenditure_date":"2018-06-07T00:00:00","report_type":"Q2","memo_code_full":null,"candidate_id":"H8SC04318","schedule_type_full":"FOR EACH INDEPENDENT EXPENDITURE MADE","candidate_office":"H","candidate_suffix":null,"memo_text":null,"payee_prefix":null,"conduit_committee_zip":null,"conduit_committee_id":null,"payee_zip":"22313","notary_sign_name":null,"is_notice":false,"election_type_full":"PRIMARY","payee_state":"VA","payee_name":"CROSSROADS MEDIA","conduit_committee_name":null,"schedule_type":"SE-F57","committee":{"filing_frequency":"Q","street_1":"2600 VIRGINIA AVE NW","cycles":[2018],"committee_id":"C90017294","committee_type":"I","cycle":2018,"zip":"20037","organization_type_full":null,"name":"CLA, INC.","party_full":null,"committee_type_full":"Independent Expenditor (Person or Group)","treasurer_name":null,"organization_type":null,"city":"WASHINGTON","street_2":"SUITE 505","state":"DC","state_full":"District Of Columbia","party":null,"candidate_ids":[],"designation":"U","designation_full":"Unauthorized"},"category_code_full":null,"conduit_committee_street1":null,"filer_prefix":null,"support_oppose_indicator":"S","candidate_name":"KIMBRELL, JOSHUA BRETT","report_year":2018,"line_number":null,"filing_form":"F5","conduit_committee_street2":null,"conduit_committee_state":null,"office_total_ytd":37824.0,"expenditure_description":"INDEPENDENT EXPENDITURE FOR","election_type":"P2018","filer_last_name":null,"payee_last_name":null,"independent_sign_date":null,"filer_first_name":null,"notary_commission_expiration_date":null,"payee_city":"ALEXANDRIA"},{"independent_sign_name":"ROZANSKY, ADAM","back_reference_schedule_name":null,"candidate_office_state":"SC","original_sub_id":null,"filer_middle_name":null,"action_code_full":"ADD","payee_street_1":"3356 ENCHANTED HILLS DRIVE","candidate_prefix":null,"candidate_last_name":"KIMBRELL","category_code":null,"candidate_party":"REP","candidate_first_name":"JOSHUA BRETT","back_reference_transaction_id":null,"image_number":"201807209117756118","memo_code":null,"candidate_middle_name":null,"dissemination_date":"2018-06-09T00:00:00","candidate_office_district":"04","pdf_url":"http:\/\/docquery.fec.gov\/cgi-bin\/fecimg\/?201807209117756118","conduit_committee_city":null,"committee_id":"C00487470","action_code":"A","payee_suffix":null,"memoed_subtotal":false,"notary_sign_date":null,"payee_first_name":null,"payee_middle_name":null,"sub_id":"4072620181576826647","expenditure_amount":20000.0,"candidate":{"idx":71726,"candidate_id":"H8SC04318","two_year_period":2018.0},"link_id":4072020181576445397,"file_number":1251346,"filer_suffix":null,"payee_street_2":null,"expenditure_date":"2018-06-08T00:00:00","report_type":"M7","memo_code_full":null,"candidate_id":"H8SC04318","schedule_type_full":"ITEMIZED INDEPENDENT EXPENDITURES","candidate_office":"H","candidate_suffix":null,"memo_text":null,"payee_prefix":null,"conduit_committee_zip":null,"conduit_committee_id":"C00487470","payee_zip":"84121","notary_sign_name":null,"is_notice":false,"election_type_full":null,"payee_state":"UT","payee_name":"G1 CONSULTING","conduit_committee_name":null,"schedule_type":"SE","committee":{"filing_frequency":"M","street_1":"2001 L ST NW STE 600","cycles":[2010,2012,2014,2016,2018],"committee_id":"C00487470","committee_type":"O","cycle":2018,"zip":"20036","organization_type_full":null,"name":"CLUB FOR GROWTH ACTION","party_full":null,"committee_type_full":"Super PAC (Independent Expenditure-Only)","treasurer_name":"ADAM ROZANSKY","organization_type":null,"city":"WASHINGTON","street_2":null,"state":"DC","state_full":"District Of Columbia","party":null,"candidate_ids":[],"designation":"U","designation_full":"Unauthorized"},"category_code_full":null,"conduit_committee_street1":null,"filer_prefix":null,"support_oppose_indicator":"S","candidate_name":"KIMBRELL, JOSHUA BRETT","report_year":2018,"line_number":"24","filing_form":"F3X","conduit_committee_street2":null,"conduit_committee_state":null,"office_total_ytd":385562.88,"expenditure_description":"PHONE BANK","election_type":"P2018","filer_last_name":"ROZANSKY","payee_last_name":null,"independent_sign_date":"2018-07-20T00:00:00","filer_first_name":"ADAM","notary_commission_expiration_date":null,"payee_city":"COTTONWOOD HEIGHTS"},{"independent_sign_name":"ROZANSKY, ADAM","back_reference_schedule_name":null,"candidate_office_state":"SC","original_sub_id":null,"filer_middle_name":null,"action_code_full":"ADD","payee_street_1":"15260 VENTURA BLVD.","candidate_prefix":null,"candidate_last_name":"KIMBRELL","category_code":null,"candidate_party":"REP","candidate_first_name":"JOSHUA BRETT","back_reference_transaction_id":null,"image_number":"201807209117756121","memo_code":null,"candidate_middle_name":null,"dissemination_date":"2018-06-08T00:00:00","candidate_office_district":"04","pdf_url":"http:\/\/docquery.fec.gov\/cgi-bin\/fecimg\/?201807209117756121","conduit_committee_city":null,"committee_id":"C00487470","action_code":"A","payee_suffix":null,"memoed_subtotal":false,"notary_sign_date":null,"payee_first_name":null,"payee_middle_name":null,"sub_id":"4072620181576826661","expenditure_amount":20000.0,"candidate":{"idx":71726,"candidate_id":"H8SC04318","two_year_period":2018.0},"link_id":4072020181576445397,"file_number":1251346,"filer_suffix":null,"payee_street_2":"STE. 1240","expenditure_date":"2018-06-08T00:00:00","report_type":"M7","memo_code_full":null,"candidate_id":"H8SC04318","schedule_type_full":"ITEMIZED INDEPENDENT EXPENDITURES","candidate_office":"H","candidate_suffix":null,"memo_text":null,"payee_prefix":null,"conduit_committee_zip":null,"conduit_committee_id":"C00487470","payee_zip":"91403","notary_sign_name":null,"is_notice":false,"election_type_full":null,"payee_state":"CA","payee_name":"TARGET ENTERPRISES","conduit_committee_name":null,"schedule_type":"SE","committee":{"filing_frequency":"M","street_1":"2001 L ST NW STE 600","cycles":[2010,2012,2014,2016,2018],"committee_id":"C00487470","committee_type":"O","cycle":2018,"zip":"20036","organization_type_full":null,"name":"CLUB FOR GROWTH ACTION","party_full":null,"committee_type_full":"Super PAC (Independent Expenditure-Only)","treasurer_name":"ADAM ROZANSKY","organization_type":null,"city":"WASHINGTON","street_2":null,"state":"DC","state_full":"District Of Columbia","party":null,"candidate_ids":[],"designation":"U","designation_full":"Unauthorized"},"category_code_full":null,"conduit_committee_street1":null,"filer_prefix":null,"support_oppose_indicator":"S","candidate_name":"KIMBRELL, JOSHUA BRETT","report_year":2018,"line_number":"24","filing_form":"F3X","conduit_committee_street2":null,"conduit_committee_state":null,"office_total_ytd":405562.88,"expenditure_description":"DIGITAL AD PLACEMENT, PRODUCTION","election_type":"P2018","filer_last_name":"ROZANSKY","payee_last_name":null,"independent_sign_date":"2018-07-20T00:00:00","filer_first_name":"ADAM","notary_commission_expiration_date":null,"payee_city":"SHERMAN OAKS"}]}
