{"api_version":"1.0","pagination":{"count":3,"last_indexes":{"last_index":"4031320181518901692","last_expenditure_amount":29575.0},"pages":1,"per_page":100},"results":[{"back_reference_schedule_name":null,"memo_text":null,"filer_suffix":null,"candidate_id":"H8TX23147","memo_code_full":null,"line_number":"24","candidate_office_state":"TX","office_total_ytd":4987.6,"pdf_url":"http:\/\/docquery.fec.gov\/cgi-bin\/fecimg\/?201805209112179638","payee_street_2":null,"file_number":1233330,"payee_name":"SOLIDARITY STRATEGIES","candidate_suffix":null,"payee_last_name":null,"original_sub_id":null,"independent_sign_date":"2018-05-18T00:00:00","candidate_office_district":"23","is_notice":false,"candidate_middle_name":null,"election_type":"P2018","candidate_prefix":null,"filer_first_name":"SARA","support_oppose_indicator":"S","candidate_party":"DEM","conduit_committee_state":null,"sub_id":"4052320181566123863","schedule_type":"SE","payee_first_name":null,"action_code_full":"CHANGE","action_code":"C","filing_form":"F3X","report_year":2018,"committee":{"cycle":2018,"cycles":[2014,2016,2018],"committee_id":"C00562777","designation_full":"Unauthorized","city":"WASHINGTON","committee_type_full":"PAC with Non-Contribution Account - Qualified","candidate_ids":[],"state":"DC","party_full":null,"street_1":"700 14TH STREET NW, 2ND FLOOR","party":null,"treasurer_name":"SAENZ, ADRIAN","name":"LATINO VICTORY FUND","committee_type":"W","street_2":null,"organization_type":null,"organization_type_full":null,"state_full":"District Of Columbia","zip":"20005","designation":"U","filing_frequency":"M"},"category_code":null,"schedule_type_full":"ITEMIZED INDEPENDENT EXPENDITURES","amendment_indicator":"A","link_id":4052020181565955851,"expenditure_amount":4987.6,"payee_zip":"20005","conduit_committee_street2":null,"filer_prefix":null,"payee_city":"WASHINGTON","filer_last_name":"LE BRUSQ","candidate_first_name":"JAY","candidate_office":"H","election_type_full":null,"notary_sign_date":null,"conduit_committee_id":"C00562777","memoed_subtotal":false,"category_code_full":null,"payee_state":"DC","payee_middle_name":null,"dissemination_date":"2018-03-05T00:00:00","independent_sign_name":"LE BRUSQ, SARA","candidate_name":"HULINGS, JAY","candidate_last_name":"HULINGS","conduit_committee_city":null,"conduit_committee_zip":null,"filer_middle_name":null,"payee_prefix":null,"committee_id":"C00562777","payee_suffix":null,"previous_file_number":1226672,"conduit_committee_street1":null,"candidate":{"idx":72871,"candidate_id":"H8TX23147","two_year_period":2018.0},"back_reference_transaction_id":null,"payee_street_1":"1090 VERMONT AVENUE NW SUITE 300","memo_code":null,"conduit_committee_name":null,"image_number":"201805209112179638","notary_commission_expiration_date":null,"expenditure_date":"2018-03-05T00:00:00","expenditure_description":"PHONE BANK AND TEXTING","report_type":"M4","notary_sign_name":null},{"back_reference_schedule_name":null,"memo_text":null,"filer_suffix":null,"candidate_id":"H8TX23147","memo_code_full":null,"line_number":"24","candidate_office_state":"TX","office_total_ytd":54575.0,"pdf_url":"http:\/\/docquery.fec.gov\/cgi-bin\/fecimg\/?201803139096539553","payee_street_2":"STE 1003","file_number":1213469,"payee_name":"MOSAIC MEDIA STRATEGY GROUP","candidate_suffix":null,"payee_last_name":null,"original_sub_id":null,"independent_sign_date":"2018-03-13T00:00:00","candidate_office_district":"23","is_notice":false,"candidate_middle_name":null,"election_type":"P2018","candidate_prefix":null,"filer_first_name":"DIANE","support_oppose_indicator":"S","candidate_party":"DEM","conduit_committee_state":null,"sub_id":"4031320181518901690","schedule_type":"SE","payee_first_name":null,"action_code_full":"ADD","action_code":"A","filing_form":"F3X","report_year":2018,"committee":{"cycle":2018,"cycles":[2002,2004,2006,2008,2010,2012,2014,2016,2018],"committee_id":"C00365536","designation_full":"Unauthorized","city":"WASHINGTON","committee_type_full":"PAC - Qualified","candidate_ids":[],"state":"DC","party_full":null,"street_1":"PO BOX 75357","party":null,"treasurer_name":"EVANS, DIANE","name":"CHC BOLD PAC","committee_type":"Q","street_2":null,"organization_type":null,"organization_type_full":null,"state_full":"District Of Columbia","zip":"20013","designation":"U","filing_frequency":"M"},"category_code":"004","schedule_type_full":"ITEMIZED INDEPENDENT EXPENDITURES","amendment_indicator":"N","link_id":4031320181518894386,"expenditure_amount":25000.0,"payee_zip":"200053939","conduit_committee_street2":null,"filer_prefix":null,"payee_city":"WASHINGTON","filer_last_name":"EVANS","candidate_first_name":"JAY","candidate_office":"H","election_type_full":null,"notary_sign_date":null,"conduit_committee_id":null,"memoed_subtotal":false,"category_code_full":"Advertising Expenses ","payee_state":"DC","payee_middle_name":null,"dissemination_date":"2018-02-21T00:00:00","independent_sign_name":"EVANS, DIANE","candidate_name":"HULINGS, JAY","candidate_last_name":"HULINGS","conduit_committee_city":null,"conduit_committee_zip":null,"filer_middle_name":null,"payee_prefix":null,"committee_id":"C00365536","payee_suffix":null,"previous_file_number":1213469,"conduit_committee_street1":null,"candidate":{"idx":72871,"candidate_id":"H8TX23147","two_year_period":2018.0},"back_reference_transaction_id":null,"payee_street_1":"1250 I ST NW","memo_code":null,"conduit_committee_name":null,"image_number":"201803139096539553","notary_commission_expiration_date":null,"expenditure_date":"2018-02-21T00:00:00","expenditure_description":"INTERNET ADVERTISING","report_type":"M3","notary_sign_name":null},{"back_reference_schedule_name":null,"memo_text":null,"filer_suffix":null,"candidate_id":"H8TX23147","memo_code_full":null,"line_number":"24","candidate_office_state":"TX","office_total_ytd":54575.0,"pdf_url":"http:\/\/docquery.fec.gov\/cgi-bin\/fecimg\/?201803139096539553","payee_street_2":"STE 300","file_number":1213469,"payee_name":"SOLIDARITY STRATEGIES","candidate_suffix":null,"payee_last_name":null,"original_sub_id":null,"independent_sign_date":"2018-03-13T00:00:00","candidate_office_district":"23","is_notice":false,"candidate_middle_name":null,"election_type":"P2018","candidate_prefix":null,"filer_first_name":"DIANE","support_oppose_indicator":"S","candidate_party":"DEM","conduit_committee_state":null,"sub_id":"4031320181518901692","schedule_type":"SE","payee_first_name":null,"action_code_full":"ADD","action_code":"A","filing_form":"F3X","report_year":2018,"committee":{"cycle":2018,"cycles":[2002,2004,2006,2008,2010,2012,2014,2016,2018],"committee_id":"C00365536","designation_full":"Unauthorized","city":"WASHINGTON","committee_type_full":"PAC - Qualified","candidate_ids":[],"state":"DC","party_full":null,"street_1":"PO BOX 75357","party":null,"treasurer_name":"EVANS, DIANE","name":"CHC BOLD PAC","committee_type":"Q","street_2":null,"organization_type":null,"organization_type_full":null,"state_full":"District Of Columbia","zip":"20013","designation":"U","filing_frequency":"M"},"category_code":"004","schedule_type_full":"ITEMIZED INDEPENDENT EXPENDITURES","amendment_indicator":"N","link_id":4031320181518894386,"expenditure_amount":29575.0,"payee_zip":"200054966","conduit_committee_street2":null,"filer_prefix":null,"payee_city":"WASHINGTON","filer_last_name":"EVANS","candidate_first_name":"JAY","candidate_office":"H","election_type_full":null,"notary_sign_date":null,"conduit_committee_id":null,"memoed_subtotal":false,"category_code_full":"Advertising Expenses ","payee_state":"DC","payee_middle_name":null,"dissemination_date":"2018-02-20T00:00:00","independent_sign_name":"EVANS, DIANE","candidate_name":"HULINGS, JAY","candidate_last_name":"HULINGS","conduit_committee_city":null,"conduit_committee_zip":null,"filer_middle_name":null,"payee_prefix":null,"committee_id":"C00365536","payee_suffix":null,"previous_file_number":1213469,"conduit_committee_street1":null,"candidate":{"idx":72871,"candidate_id":"H8TX23147","two_year_period":2018.0},"back_reference_transaction_id":null,"payee_street_1":"1090 VERMONT AVE NW","memo_code":null,"conduit_committee_name":null,"image_number":"201803139096539553","notary_commission_expiration_date":null,"expenditure_date":"2018-02-20T00:00:00","expenditure_description":"DIRECT MAIL","report_type":"M3","notary_sign_name":null}]}
